git_dependency_installer/__init__.py
git_dependency_installer/dependency_lock_manager.py
git_dependency_installer/dependency_manager.py
git_dependency_installer/git_dependency.py
git_dependency_installer/pip_helper.py
git_dependency_installer/setup_helper.py
git_dependency_installer/tools.py
git_dependency_installer/version_resolver.py
git_dependency_installer-1.0.3.dist-info/LICENSE
git_dependency_installer-1.0.3.dist-info/LICENSE.txt
git_dependency_installer-1.0.3.dist-info/WHEEL
git_dependency_installer-1.0.3.dist-info/METADATA
git_dependency_installer-1.0.3.dist-info/RECORD
