Metadata-Version: 2.1
Name: git_dependency_installer
Version: 1.0.3
Summary: SDK that helps to manage dependencies directly from git repositories.
Author-email: Deividas Tamkus <deividas@idenfy.com>
Classifier: License :: OSI Approved :: MIT License
Project-URL: Home, https://github.com/idenfy/GitDependencyInstaller.git
